icm/__init__.py
icm/meteo.py
meteo_icm-0.0.1.dist-info/LICENSE
meteo_icm-0.0.1.dist-info/METADATA
meteo_icm-0.0.1.dist-info/WHEEL
meteo_icm-0.0.1.dist-info/top_level.txt
meteo_icm-0.0.1.dist-info/RECORD
